config_getter/__init__.py
config_getter/cli.py
config_getter-0.0.6.dist-info/METADATA
config_getter-0.0.6.dist-info/WHEEL
config_getter-0.0.6.dist-info/entry_points.txt
config_getter-0.0.6.dist-info/licenses/LICENSE
config_getter-0.0.6.dist-info/RECORD
