Metadata-Version: 2.4
Name: config-getter
Version: 0.0.6
Summary: Get common config for different types of projects
Project-URL: Homepage, https://github.com/cooperellidge/config-getter
Project-URL: Repository, https://github.com/cooperellidge/config-getter
Author-email: Cooper Ellidge <cooper.ellidge@gmail.com>
License: MIT License
License-File: LICENSE
Requires-Python: >=3.13
Requires-Dist: requests>=2.32.3
Requires-Dist: typer>=0.15.1
